turkish_validator/__init__.py
turkish_validator/tr_validator.py
turkish_validator-0.1.4.dist-info/LICENSE.MD
turkish_validator-0.1.4.dist-info/WHEEL
turkish_validator-0.1.4.dist-info/METADATA
turkish_validator-0.1.4.dist-info/RECORD
