Metadata-Version: 2.1
Name: turkish-validator
Version: 0.1.4
Summary: A package for validating Turkish ID and tax numbers.
Home-page: https://github.com/hasanozdem1r/turkish_validator
Keywords: turkish,validator,ID,tax number
Author: Hasan Özdemir
Author-email: hasanozdemir1@trakya.edu.tr
Requires-Python: >=3.9,<4.0
Classifier: Programming Language :: Python :: 3
Classifier: Programming Language :: Python :: 3.9
Classifier: Programming Language :: Python :: 3.10
Classifier: Programming Language :: Python :: 3.11
Requires-Dist: black (>=23.1.0,<24.0.0)
Requires-Dist: pre-commit (>=3.3.3,<4.0.0)
Project-URL: Documentation, https://github.com/hasanozdem1r/turkish_validator#readme
Project-URL: Repository, https://github.com/hasanozdem1r/turkish_validator
